plunetapi/__init__.py
plunetapi/server.py
plunetapi/webservice.py
plunetapi-0.4.0.dist-info/LICENCE
plunetapi-0.4.0.dist-info/METADATA
plunetapi-0.4.0.dist-info/WHEEL
plunetapi-0.4.0.dist-info/top_level.txt
plunetapi-0.4.0.dist-info/RECORD
