Metadata-Version: 2.2
Name: plunetapi
Version: 0.4.0
Summary: Thin wrapper for the Plunet SOAP API.
Author-email: Henrik Kühnemann <hello@yellownape.se>
Project-URL: Homepage, https://github.com/kuhnemann/plunet-api
Keywords: plunet,api,translation,localization,tms
Classifier: License :: OSI Approved :: MIT License
Classifier: Programming Language :: Python
Classifier: Programming Language :: Python :: 3
Requires-Python: >=3.9
License-File: LICENCE
Requires-Dist: zeep>=4.3.1
Provides-Extra: dev
Requires-Dist: black; extra == "dev"
Requires-Dist: bumpver; extra == "dev"
Requires-Dist: isort; extra == "dev"
Requires-Dist: pip-tools; extra == "dev"
Requires-Dist: pytest; extra == "dev"
